isi_sdk_7_2/__init__.py
isi_sdk_7_2/api_client.py
isi_sdk_7_2/configuration.py
isi_sdk_7_2/rest.py
isi_sdk_7_2/api/__init__.py
isi_sdk_7_2/api/audit_api.py
isi_sdk_7_2/api/auth_api.py
isi_sdk_7_2/api/auth_groups_api.py
isi_sdk_7_2/api/auth_providers_api.py
isi_sdk_7_2/api/auth_roles_api.py
isi_sdk_7_2/api/auth_users_api.py
isi_sdk_7_2/api/cloud_api.py
isi_sdk_7_2/api/cluster_api.py
isi_sdk_7_2/api/debug_api.py
isi_sdk_7_2/api/dedupe_api.py
isi_sdk_7_2/api/event_api.py
isi_sdk_7_2/api/filepool_api.py
isi_sdk_7_2/api/filesystem_api.py
isi_sdk_7_2/api/fsa_api.py
isi_sdk_7_2/api/job_api.py
isi_sdk_7_2/api/license_api.py
isi_sdk_7_2/api/namespace_api.py
isi_sdk_7_2/api/protocols_api.py
isi_sdk_7_2/api/protocols_hdfs_api.py
isi_sdk_7_2/api/quota_api.py
isi_sdk_7_2/api/quota_quotas_api.py
isi_sdk_7_2/api/quota_reports_api.py
isi_sdk_7_2/api/remotesupport_api.py
isi_sdk_7_2/api/snapshot_api.py
isi_sdk_7_2/api/snapshot_changelists_api.py
isi_sdk_7_2/api/snapshot_snapshots_api.py
isi_sdk_7_2/api/statistics_api.py
isi_sdk_7_2/api/storagepool_api.py
isi_sdk_7_2/api/sync_api.py
isi_sdk_7_2/api/sync_policies_api.py
isi_sdk_7_2/api/sync_reports_api.py
isi_sdk_7_2/api/sync_target_api.py
isi_sdk_7_2/api/worm_api.py
isi_sdk_7_2/api/zones_api.py
isi_sdk_7_2/api/zones_summary_api.py
isi_sdk_7_2/models/__init__.py
isi_sdk_7_2/models/access_point_create_params.py
isi_sdk_7_2/models/acl_object.py
isi_sdk_7_2/models/ads_provider_controllers.py
isi_sdk_7_2/models/ads_provider_controllers_controller.py
isi_sdk_7_2/models/ads_provider_domains.py
isi_sdk_7_2/models/ads_provider_domains_domain.py
isi_sdk_7_2/models/ads_provider_search.py
isi_sdk_7_2/models/ads_provider_search_object.py
isi_sdk_7_2/models/audit_settings.py
isi_sdk_7_2/models/audit_settings_settings.py
isi_sdk_7_2/models/audit_topic.py
isi_sdk_7_2/models/audit_topic_create_params.py
isi_sdk_7_2/models/audit_topic_extended.py
isi_sdk_7_2/models/audit_topics.py
isi_sdk_7_2-0.2.11.dist-info/DESCRIPTION.rst
isi_sdk_7_2-0.2.11.dist-info/METADATA
isi_sdk_7_2-0.2.11.dist-info/RECORD
isi_sdk_7_2-0.2.11.dist-info/WHEEL
isi_sdk_7_2-0.2.11.dist-info/metadata.json
isi_sdk_7_2-0.2.11.dist-info/top_level.txt
